MANIFEST.in
README.md
setup.py
S2_TOA_TO_LAI/.scihub_auth
S2_TOA_TO_LAI/TOA2LAI_S2.py
S2_TOA_TO_LAI/VERSION
S2_TOA_TO_LAI/__init__.py
S2_TOA_TO_LAI/create_logger.py
S2_TOA_TO_LAI/get_scihub_pass.py
S2_TOA_TO_LAI/nnModel.py
S2_TOA_TO_LAI/parse_aoi.py
S2_TOA_TO_LAI/query.py
S2_TOA_TO_LAI.egg-info/PKG-INFO
S2_TOA_TO_LAI.egg-info/SOURCES.txt
S2_TOA_TO_LAI.egg-info/dependency_links.txt
S2_TOA_TO_LAI.egg-info/requires.txt
S2_TOA_TO_LAI.egg-info/top_level.txt
S2_TOA_TO_LAI/data/Third_comps.npz
S2_TOA_TO_LAI/data/Third_inv_gp.npz
S2_TOA_TO_LAI/data/nnLai.npz