Metadata-Version: 2.1
Name: S2-TOA-TO-LAI
Version: 2.0.0
Summary: From Sentinel 2 TOA to LAI
Home-page: https://github.com/MarcYin/S2_TOA_TO_LAI
Author: Feng Yin
Author-email: ucfafyi@ucl.ac.uk
License: GNU Affero General Public License v3.0
Platform: UNKNOWN
Classifier: Development Status :: 4 - Beta
Classifier: Programming Language :: Python :: 2.7
Classifier: Programming Language :: Python :: 3.6
